DESCRIPTION.rst
LICENSE.txt
MANIFEST.in
README.rst
requirements.txt
setup.cfg
setup.py
rewind/__init__.py
rewind/client/__init__.py
rewind/client/test/__init__.py
rewind/client/test/test_client.py
rewind/client/test/test_code.py
rewind_client.egg-info/PKG-INFO
rewind_client.egg-info/SOURCES.txt
rewind_client.egg-info/dependency_links.txt
rewind_client.egg-info/namespace_packages.txt
rewind_client.egg-info/requires.txt
rewind_client.egg-info/top_level.txt