Metadata-Version: 1.1
Name: rewind-client
Version: 0.3.0
Summary: Python client for Rewind event store.
Home-page: https://github.com/JensRantil/rewind-client
Author: Jens Rantil
Author-email: jens.rantil@gmail.com
License: GNU AGPL, version 3
Keywords: CQRS,event sourcing,ZeroMQ
Platform: UNKNOWN
Classifier: Development Status :: 4 - Beta
Classifier: Environment :: No Input/Output (Daemon)
Classifier: Intended Audience :: Other Audience
Classifier: License :: OSI Approved :: MIT License
Classifier: Natural Language :: English
Classifier: Operating System :: OS Independent
Classifier: Programming Language :: Python :: 2.7
Classifier: Programming Language :: Python :: 3.2
Classifier: Topic :: Software Development :: Object Brokering
Classifier: Topic :: System :: Distributed Computing
